odoo10_addon_report_qweb_element_page_visibility-10.0.1.0.0-py2.7-nspkg.pth
odoo10_addon_report_qweb_element_page_visibility-10.0.1.0.0.dist-info/top_level.txt
odoo10_addon_report_qweb_element_page_visibility-10.0.1.0.0.dist-info/WHEEL
odoo10_addon_report_qweb_element_page_visibility-10.0.1.0.0.dist-info/RECORD
odoo10_addon_report_qweb_element_page_visibility-10.0.1.0.0.dist-info/metadata.json
odoo10_addon_report_qweb_element_page_visibility-10.0.1.0.0.dist-info/DESCRIPTION.rst
odoo10_addon_report_qweb_element_page_visibility-10.0.1.0.0.dist-info/METADATA
odoo10_addon_report_qweb_element_page_visibility-10.0.1.0.0.dist-info/namespace_packages.txt
odoo/addons/report_qweb_element_page_visibility/__manifest__.py
odoo/addons/report_qweb_element_page_visibility/__init__.py
odoo/addons/report_qweb_element_page_visibility/README.rst
odoo/addons/report_qweb_element_page_visibility/views/layouts.xml
odoo/addons/report_qweb_element_page_visibility/static/description/icon.png
