Metadata-Version: 2.0
Name: odoo10-addon-report-qweb-element-page-visibility
Version: 10.0.1.0.0
Summary: Report Qweb Element Page Visibility
Home-page: https://odoo-community.org/
Author: Agile Business Group, Odoo Community Association (OCA)
Author-email: support@odoo-community.org
License: AGPL-3
Platform: UNKNOWN
Requires-Dist: odoo (<10.1dev,>=10.0)
Classifier: Programming Language :: Python :: 2.7
Classifier: Framework :: Odoo
Classifier: License :: OSI Approved :: GNU Affero General Public License v3
